pycde/ESIPrimitives.sv
pycde/__init__.py
pycde/common.py
pycde/constructs.py
pycde/devicedb.py
pycde/esi.py
pycde/fsm.py
pycde/handshake.py
pycde/instance.py
pycde/module.py
pycde/ndarray.py
pycde/seq.py
pycde/signals.py
pycde/support.py
pycde/system.py
pycde/testing.py
pycde/types.py
pycde/bsp/Makefile.xrt.mk
pycde/bsp/__init__.py
pycde/bsp/common.py
pycde/bsp/cosim.py
pycde/bsp/dma.py
pycde/bsp/xrt.ini
pycde/bsp/xrt.py
pycde/bsp/xrt_package.tcl
pycde/bsp/xrt_vitis.cfg
pycde/bsp/xsim.tcl
pycde/circt/__init__.py
pycde/circt/ir.py
pycde/circt/passmanager.py
pycde/circt/rewrite.py
pycde/circt/support.py
pycde/circt/_mlir_libs/PyCDE_CIRCTPythonCAPI.dll
pycde/circt/_mlir_libs/PyCDE_CIRCTPythonCAPI.lib
pycde/circt/_mlir_libs/__init__.py
pycde/circt/_mlir_libs/_circt.cp313-win_amd64.pyd
pycde/circt/_mlir_libs/_mlir.cp313-win_amd64.pyd
pycde/circt/_mlir_libs/zlib1.dll
pycde/circt/_mlir_libs/_mlir/__init__.pyi
pycde/circt/_mlir_libs/_mlir/ir.pyi
pycde/circt/_mlir_libs/_mlir/passmanager.pyi
pycde/circt/dialects/_arith_enum_gen.py
pycde/circt/dialects/_arith_ops_gen.py
pycde/circt/dialects/_comb_ops_gen.py
pycde/circt/dialects/_dbg_ops_gen.py
pycde/circt/dialects/_emit_ops_gen.py
pycde/circt/dialects/_esi_ops_gen.py
pycde/circt/dialects/_fsm_ops_gen.py
pycde/circt/dialects/_handshake_ops_gen.py
pycde/circt/dialects/_hw_ops_gen.py
pycde/circt/dialects/_hwarith_ops_gen.py
pycde/circt/dialects/_index_enum_gen.py
pycde/circt/dialects/_index_ops_gen.py
pycde/circt/dialects/_ltl_ops_gen.py
pycde/circt/dialects/_msft_ops_gen.py
pycde/circt/dialects/_ods_common.py
pycde/circt/dialects/_om_ops_gen.py
pycde/circt/dialects/_rtg_ops_gen.py
pycde/circt/dialects/_rtgtest_ops_gen.py
pycde/circt/dialects/_scf_ops_gen.py
pycde/circt/dialects/_seq_ops_gen.py
pycde/circt/dialects/_sv_ops_gen.py
pycde/circt/dialects/_synth_ops_gen.py
pycde/circt/dialects/_verif_ops_gen.py
pycde/circt/dialects/arith.py
pycde/circt/dialects/comb.py
pycde/circt/dialects/debug.py
pycde/circt/dialects/emit.py
pycde-0.9.0.dist-info/METADATA
pycde-0.9.0.dist-info/WHEEL
pycde-0.9.0.dist-info/top_level.txt
pycde-0.9.0.dist-info/RECORD
