Metadata-Version: 2.4
Name: pycde
Version: 0.9.0
Summary: Python CIRCT Design Entry
Author-email: John Demme <John.Demme@microsoft.com>
Project-URL: Homepage, https://circt.llvm.org/docs/PyCDE/
Requires-Python: >=3.8
Requires-Dist: numpy
